README.md
setup.py
naxida/__init__.py
naxida/__version__.py
naxida.egg-info/PKG-INFO
naxida.egg-info/SOURCES.txt
naxida.egg-info/dependency_links.txt
naxida.egg-info/requires.txt
naxida.egg-info/top_level.txt
naxida/bot/__init__.py
naxida/bot/_bot_main.py
naxida/bot/charming.py
naxida/bot/config.py
naxida/bot/insert.py
naxida/bot/manual.py
naxida/bot/plugin.py
naxida/bot/receive.py
naxida/bot/send.py